Metadata-Version: 2.1
Name: isEven
Version: 0.1.0
Summary: Simple library to check if a number is even
Home-page: https://github.com/juanbenitezdev/isEven
Author: Juan Benitez
Author-email: juanbenitezdev@gmail.com
License: MIT
Download-URL: https://github.com/JuanBenitezDev/isEven/archive/v0.1.0.tar.gz
Keywords: Even,Integer,Math
Platform: UNKNOWN
Classifier: Development Status :: 5 - Production/Stable
Classifier: Intended Audience :: Developers
Classifier: Topic :: Software Development :: Build Tools
Classifier: License :: OSI Approved :: MIT License
Classifier: Programming Language :: Python :: 3
